thousandeyes_sdk/usage/__init__.py
thousandeyes_sdk/usage/py.typed
thousandeyes_sdk/usage/api/__init__.py
thousandeyes_sdk/usage/api/quotas_api.py
thousandeyes_sdk/usage/api/usage_api.py
thousandeyes_sdk/usage/models/__init__.py
thousandeyes_sdk/usage/models/account_group_quota.py
thousandeyes_sdk/usage/models/allocation_unit_usage_breakdown.py
thousandeyes_sdk/usage/models/endpoint_agents_embedded.py
thousandeyes_sdk/usage/models/endpoint_agents_essentials.py
thousandeyes_sdk/usage/models/endpoint_agents_usage.py
thousandeyes_sdk/usage/models/enterprise_agent_units.py
thousandeyes_sdk/usage/models/enterprise_agent_units_by_test_owner_account_group.py
thousandeyes_sdk/usage/models/enterprise_agents.py
thousandeyes_sdk/usage/models/enterprise_agents_usage.py
thousandeyes_sdk/usage/models/error.py
thousandeyes_sdk/usage/models/expand_usage_options.py
thousandeyes_sdk/usage/models/link.py
thousandeyes_sdk/usage/models/organization_quota.py
thousandeyes_sdk/usage/models/organization_quota_assignment.py
thousandeyes_sdk/usage/models/organization_quota_unassignment.py
thousandeyes_sdk/usage/models/organizations_quotas_assign.py
thousandeyes_sdk/usage/models/organizations_quotas_unassign.py
thousandeyes_sdk/usage/models/pagination_links.py
thousandeyes_sdk/usage/models/quota.py
thousandeyes_sdk/usage/models/quotas.py
thousandeyes_sdk/usage/models/quotas_assign_request.py
thousandeyes_sdk/usage/models/quotas_assign_response.py
thousandeyes_sdk/usage/models/quotas_unassign.py
thousandeyes_sdk/usage/models/self_links.py
thousandeyes_sdk/usage/models/test_usage.py
thousandeyes_sdk/usage/models/tests_usage.py
thousandeyes_sdk/usage/models/unauthorized_error.py
thousandeyes_sdk/usage/models/unit_allocation_summary.py
thousandeyes_sdk/usage/models/units_by_tests.py
thousandeyes_sdk/usage/models/usage.py
thousandeyes_sdk/usage/models/usage_details.py
thousandeyes_sdk/usage/models/usage_quota.py
thousandeyes_sdk/usage/models/validation_error.py
thousandeyes_sdk_usage-2.23.0.dist-info/licenses/LICENSE
thousandeyes_sdk_usage-2.23.0.dist-info/licenses/NOTICE
thousandeyes_sdk_usage-2.23.0.dist-info/METADATA
thousandeyes_sdk_usage-2.23.0.dist-info/WHEEL
thousandeyes_sdk_usage-2.23.0.dist-info/top_level.txt
thousandeyes_sdk_usage-2.23.0.dist-info/RECORD
